static_vars.py
static_vars-0.0.0.dist-info/entry_points.txt
static_vars-0.0.0.dist-info/LICENSE
static_vars-0.0.0.dist-info/WHEEL
static_vars-0.0.0.dist-info/METADATA
static_vars-0.0.0.dist-info/RECORD
